{"nodes": [{"id": "basicgeometry_BasicGeometry", "label": "BasicGeometry", "file_type": "code", "source_file": "FishSim/BasicGeometry.cs", "source_location": null, "source_url": null, "captured_at": null, "author": null, "contributor": null}, {"id": "basicgeometry_CreateCube", "label": "BasicGeometry.CreateCube", "file_type": "code", "source_file": "FishSim/BasicGeometry.cs", "source_location": "line 36", "source_url": null, "captured_at": null, "author": null, "contributor": null}, {"id": "basicgeometry_CreateRoundedCube", "label": "BasicGeometry.CreateRoundedCube", "file_type": "code", "source_file": "FishSim/BasicGeometry.cs", "source_location": "line 107", "source_url": null, "captured_at": null, "author": null, "contributor": null}, {"id": "basicgeometry_CreateSphere", "label": "BasicGeometry.CreateSphere", "file_type": "code", "source_file": "FishSim/BasicGeometry.cs", "source_location": "line 192", "source_url": null, "captured_at": null, "author": null, "contributor": null}, {"id": "basicgeometry_CreateHalfSphere", "label": "BasicGeometry.CreateHalfSphere", "file_type": "code", "source_file": "FishSim/BasicGeometry.cs", "source_location": "line 202", "source_url": null, "captured_at": null, "author": null, "contributor": null}, {"id": "basicgeometry_Draw", "label": "BasicGeometry.Draw", "file_type": "code", "source_file": "FishSim/BasicGeometry.cs", "source_location": "line 18", "source_url": null, "captured_at": null, "author": null, "contributor": null}, {"id": "basicgeometry_DrawWithoutEffect", "label": "BasicGeometry.DrawWithoutEffect", "file_type": "code", "source_file": "FishSim/BasicGeometry.cs", "source_location": "line 26", "source_url": null, "captured_at": null, "author": null, "contributor": null}], "edges": [{"source": "basicgeometry_Draw", "target": "basicgeometry_DrawWithoutEffect", "relation": "calls", "confidence": "EXTRACTED", "confidence_score": 1.0, "source_file": "FishSim/BasicGeometry.cs", "source_location": "line 24", "weight": 1.0}, {"source": "basicgeometry_CreateCube", "target": "basicgeometry_BasicGeometry", "relation": "calls", "confidence": "EXTRACTED", "confidence_score": 1.0, "source_file": "FishSim/BasicGeometry.cs", "source_location": "line 38", "weight": 1.0}, {"source": "basicgeometry_CreateSphere", "target": "basicgeometry_CreateHalfSphere", "relation": "calls", "confidence": "INFERRED", "confidence_score": 0.95, "source_file": "FishSim/BasicGeometry.cs", "source_location": "line 193", "weight": 0.8}, {"source": "basicgeometry_CreateSphere", "target": "basicgeometry_CreateHalfSphere", "relation": "semantically_similar_to", "confidence": "INFERRED", "confidence_score": 0.85, "source_file": "FishSim/BasicGeometry.cs", "source_location": null, "weight": 0.7}, {"source": "basicgeometry_CreateCube", "target": "basicgeometry_CreateRoundedCube", "relation": "semantically_similar_to", "confidence": "INFERRED", "confidence_score": 0.85, "source_file": "FishSim/BasicGeometry.cs", "source_location": null, "weight": 0.7}], "hyperedges": []}